_adf.cp37-win_amd64.pyd
_epanet2.cp37-win_amd64.pyd
_pdd.cp37-win_amd64.pyd
EPANETTOOLS-1.0.0.dist-info/METADATA
EPANETTOOLS-1.0.0.dist-info/RECORD
EPANETTOOLS-1.0.0.dist-info/WHEEL
EPANETTOOLS-1.0.0.dist-info/entry_points.txt
EPANETTOOLS-1.0.0.dist-info/top_level.txt
epanettools/__init__.py
epanettools/__main__.py
epanettools/adf.i
epanettools/adf.py
epanettools/adf_wrap.cxx
epanettools/cli.py
epanettools/epanet2.i
epanettools/epanet2.py
epanettools/epanet2_wrap.c
epanettools/epanettools.py
epanettools/patch.c
epanettools/patch.h
epanettools/pdd.i
epanettools/pdd.py
epanettools/pdd_class_wrapper.py
epanettools/pdd_wrap.cxx
epanettools/tools.py
epanettools/adf/adfandenergycalc.h
epanettools/adf/callepanet.cc
epanettools/adf/callepanet.h
epanettools/adf/main.cc
epanettools/epanet/enumstxt.h
epanettools/epanet/epanet.c
epanettools/epanet/epanet2.h
epanettools/epanet/funcs.h
epanettools/epanet/hash.c
epanettools/epanet/hash.h
epanettools/epanet/hydraul.c
epanettools/epanet/inpfile.c
epanettools/epanet/input1.c
epanettools/epanet/input2.c
epanettools/epanet/input3.c
epanettools/epanet/mempool.c
epanettools/epanet/mempool.h
epanettools/epanet/output.c
epanettools/epanet/quality.c
epanettools/epanet/report.c
epanettools/epanet/rules.c
epanettools/epanet/smatrix.c
epanettools/epanet/text.h
epanettools/epanet/toolkit.h
epanettools/epanet/types.h
epanettools/epanet/vars.h
epanettools/examples/__init__.py
epanettools/examples/simple/Net1.inp
epanettools/examples/simple/Net2.inp
epanettools/examples/simple/Net3.inp
epanettools/examples/simple/__init__.py
epanettools/examples/simple/epanet2_test.py
epanettools/pdd/README.txt
epanettools/pdd/emitter_analysis.cpp
epanettools/pdd/include.h
epanettools/pdd/mods.cpp
epanettools/pdd/wrap.cpp
epanettools/pdd/wrapper.h
